{
  "pair": "EURJPY",
  "tf": "m15",
  "sourceUpdatedAt": "2026-07-10T11:43:21.963Z",
  "version": 1,
  "generatedAt": "2026-07-10T12:07:48.223Z",
  "sampleCount": 3919,
  "horizons": [
    1,
    5,
    20
  ],
  "performance": {
    "halfLifeSamples": 100,
    "horizons": [
      {
        "horizon": 1,
        "models": {
          "signal": {
            "hits": 1932,
            "total": 3919,
            "accuracy": 0.4929829038019903,
            "decayedHits": 68.09528994001798,
            "decayedTotal": 144.770081710854,
            "ewmaAccuracy": 0.47036852597778567
          },
          "drift": {
            "hits": 1953,
            "total": 3919,
            "accuracy": 0.498341413625925,
            "decayedHits": 70.84325114298446,
            "decayedTotal": 144.770081710854,
            "ewmaAccuracy": 0.48935008052615514
          },
          "regime": {
            "hits": 2063,
            "total": 3919,
            "accuracy": 0.5264097984179638,
            "decayedHits": 71.00424023774343,
            "decayedTotal": 144.770081710854,
            "ewmaAccuracy": 0.490462113432792
          }
        }
      },
      {
        "horizon": 5,
        "models": {
          "signal": {
            "hits": 1970,
            "total": 3915,
            "accuracy": 0.5031928480204342,
            "decayedHits": 74.08714613458461,
            "decayedTotal": 144.7700817108475,
            "ewmaAccuracy": 0.5117572999824681
          },
          "drift": {
            "hits": 1951,
            "total": 3915,
            "accuracy": 0.4983397190293742,
            "decayedHits": 71.68203437984027,
            "decayedTotal": 144.7700817108475,
            "ewmaAccuracy": 0.4951439795621059
          },
          "regime": {
            "hits": 1997,
            "total": 3915,
            "accuracy": 0.5100893997445721,
            "decayedHits": 69.21040910840577,
            "decayedTotal": 144.7700817108475,
            "ewmaAccuracy": 0.4780712167217067
          }
        }
      },
      {
        "horizon": 20,
        "models": {
          "signal": {
            "hits": 1949,
            "total": 3900,
            "accuracy": 0.49974358974358973,
            "decayedHits": 77.48696220557568,
            "decayedTotal": 144.7700817108215,
            "ewmaAccuracy": 0.5352415450062121
          },
          "drift": {
            "hits": 1981,
            "total": 3900,
            "accuracy": 0.507948717948718,
            "decayedHits": 84.0433295882247,
            "decayedTotal": 144.7700817108215,
            "ewmaAccuracy": 0.5805296826184114
          },
          "regime": {
            "hits": 1947,
            "total": 3900,
            "accuracy": 0.49923076923076926,
            "decayedHits": 75.29292285796917,
            "decayedTotal": 144.7700817108215,
            "ewmaAccuracy": 0.5200862082012699
          }
        }
      }
    ]
  },
  "weights": {
    "temperature": 0.08,
    "minSamples": 30,
    "horizons": [
      {
        "horizon": 1,
        "sampleCount": 3919,
        "fallback": false,
        "weights": {
          "signal": 0.3433163934242184,
          "drift": 0.38084424700276803,
          "regime": 0.27583935957301364
        }
      },
      {
        "horizon": 5,
        "sampleCount": 3915,
        "fallback": false,
        "weights": {
          "signal": 0.47144663992386576,
          "drift": 0.33515999904542654,
          "regime": 0.1933933610307077
        }
      },
      {
        "horizon": 20,
        "sampleCount": 3900,
        "fallback": false,
        "weights": {
          "signal": 0.32697348623476447,
          "drift": 0.5039360692437441,
          "regime": 0.16909044452149136
        }
      }
    ]
  },
  "calibration": {
    "horizons": [
      {
        "horizon": 1,
        "table": {
          "binCount": 10,
          "alpha": 2,
          "sampleCount": 3919,
          "bins": [
            {
              "index": 0,
              "lower": 0,
              "upper": 0.1,
              "midpoint": 0.05,
              "count": 0,
              "positives": 0,
              "averagePrediction": 0.05,
              "observedFrequency": 0.05,
              "calibratedProbability": 0.05
            },
            {
              "index": 1,
              "lower": 0.1,
              "upper": 0.2,
              "midpoint": 0.15000000000000002,
              "count": 0,
              "positives": 0,
              "averagePrediction": 0.15000000000000002,
              "observedFrequency": 0.15000000000000002,
              "calibratedProbability": 0.15000000000000002
            },
            {
              "index": 2,
              "lower": 0.2,
              "upper": 0.3,
              "midpoint": 0.25,
              "count": 2,
              "positives": 1,
              "averagePrediction": 0.28945097014918625,
              "observedFrequency": 0.5,
              "calibratedProbability": 0.39603024574669193
            },
            {
              "index": 3,
              "lower": 0.3,
              "upper": 0.4,
              "midpoint": 0.35,
              "count": 44,
              "positives": 17,
              "averagePrediction": 0.3691856985127661,
              "observedFrequency": 0.391304347826087,
              "calibratedProbability": 0.39603024574669193
            },
            {
              "index": 4,
              "lower": 0.4,
              "upper": 0.5,
              "midpoint": 0.45,
              "count": 1750,
              "positives": 869,
              "averagePrediction": 0.4671302959698224,
              "observedFrequency": 0.4965753424657534,
              "calibratedProbability": 0.4965753424657534
            },
            {
              "index": 5,
              "lower": 0.5,
              "upper": 0.6,
              "midpoint": 0.55,
              "count": 2109,
              "positives": 1056,
              "averagePrediction": 0.5325782836277555,
              "observedFrequency": 0.5007105637138797,
              "calibratedProbability": 0.5007105637138797
            },
            {
              "index": 6,
              "lower": 0.6,
              "upper": 0.7,
              "midpoint": 0.6499999999999999,
              "count": 14,
              "positives": 8,
              "averagePrediction": 0.6203596076938878,
              "observedFrequency": 0.5625,
              "calibratedProbability": 0.5625
            },
            {
              "index": 7,
              "lower": 0.7,
              "upper": 0.8,
              "midpoint": 0.75,
              "count": 0,
              "positives": 0,
              "averagePrediction": 0.75,
              "observedFrequency": 0.75,
              "calibratedProbability": 0.75
            },
            {
              "index": 8,
              "lower": 0.8,
              "upper": 0.9,
              "midpoint": 0.8500000000000001,
              "count": 0,
              "positives": 0,
              "averagePrediction": 0.8500000000000001,
              "observedFrequency": 0.8500000000000001,
              "calibratedProbability": 0.8500000000000001
            },
            {
              "index": 9,
              "lower": 0.9,
              "upper": 1,
              "midpoint": 0.95,
              "count": 0,
              "positives": 0,
              "averagePrediction": 0.95,
              "observedFrequency": 0.95,
              "calibratedProbability": 0.95
            }
          ]
        }
      },
      {
        "horizon": 5,
        "table": {
          "binCount": 10,
          "alpha": 2,
          "sampleCount": 3915,
          "bins": [
            {
              "index": 0,
              "lower": 0,
              "upper": 0.1,
              "midpoint": 0.05,
              "count": 0,
              "positives": 0,
              "averagePrediction": 0.05,
              "observedFrequency": 0.05,
              "calibratedProbability": 0.05
            },
            {
              "index": 1,
              "lower": 0.1,
              "upper": 0.2,
              "midpoint": 0.15000000000000002,
              "count": 0,
              "positives": 0,
              "averagePrediction": 0.15000000000000002,
              "observedFrequency": 0.15000000000000002,
              "calibratedProbability": 0.15000000000000002
            },
            {
              "index": 2,
              "lower": 0.2,
              "upper": 0.3,
              "midpoint": 0.25,
              "count": 15,
              "positives": 4,
              "averagePrediction": 0.27265197531146157,
              "observedFrequency": 0.29411764705882354,
              "calibratedProbability": 0.29411764705882354
            },
            {
              "index": 3,
              "lower": 0.3,
              "upper": 0.4,
              "midpoint": 0.35,
              "count": 226,
              "positives": 130,
              "averagePrediction": 0.3741925619068857,
              "observedFrequency": 0.5745614035087719,
              "calibratedProbability": 0.50375045382137
            },
            {
              "index": 4,
              "lower": 0.4,
              "upper": 0.5,
              "midpoint": 0.45,
              "count": 1604,
              "positives": 792,
              "averagePrediction": 0.45751552155847647,
              "observedFrequency": 0.4937733499377335,
              "calibratedProbability": 0.50375045382137
            },
            {
              "index": 5,
              "lower": 0.5,
              "upper": 0.6,
              "midpoint": 0.55,
              "count": 1815,
              "positives": 936,
              "averagePrediction": 0.5420875640566476,
              "observedFrequency": 0.5156851953769951,
              "calibratedProbability": 0.5156851953769951
            },
            {
              "index": 6,
              "lower": 0.6,
              "upper": 0.7,
              "midpoint": 0.6499999999999999,
              "count": 253,
              "positives": 135,
              "averagePrediction": 0.6211479176585298,
              "observedFrequency": 0.5333333333333333,
              "calibratedProbability": 0.5311111111111111
            },
            {
              "index": 7,
              "lower": 0.7,
              "upper": 0.8,
              "midpoint": 0.75,
              "count": 2,
              "positives": 0,
              "averagePrediction": 0.7375357404461225,
              "observedFrequency": 0.25,
              "calibratedProbability": 0.5311111111111111
            },
            {
              "index": 8,
              "lower": 0.8,
              "upper": 0.9,
              "midpoint": 0.8500000000000001,
              "count": 0,
              "positives": 0,
              "averagePrediction": 0.8500000000000001,
              "observedFrequency": 0.8500000000000001,
              "calibratedProbability": 0.8500000000000001
            },
            {
              "index": 9,
              "lower": 0.9,
              "upper": 1,
              "midpoint": 0.95,
              "count": 0,
              "positives": 0,
              "averagePrediction": 0.95,
              "observedFrequency": 0.95,
              "calibratedProbability": 0.95
            }
          ]
        }
      },
      {
        "horizon": 20,
        "table": {
          "binCount": 10,
          "alpha": 2,
          "sampleCount": 3900,
          "bins": [
            {
              "index": 0,
              "lower": 0,
              "upper": 0.1,
              "midpoint": 0.05,
              "count": 0,
              "positives": 0,
              "averagePrediction": 0.05,
              "observedFrequency": 0.05,
              "calibratedProbability": 0.05
            },
            {
              "index": 1,
              "lower": 0.1,
              "upper": 0.2,
              "midpoint": 0.15000000000000002,
              "count": 11,
              "positives": 2,
              "averagePrediction": 0.18060874121271253,
              "observedFrequency": 0.23076923076923078,
              "calibratedProbability": 0.23076923076923078
            },
            {
              "index": 2,
              "lower": 0.2,
              "upper": 0.3,
              "midpoint": 0.25,
              "count": 344,
              "positives": 210,
              "averagePrediction": 0.2695520566272847,
              "observedFrequency": 0.6098265895953757,
              "calibratedProbability": 0.51298503573252
            },
            {
              "index": 3,
              "lower": 0.3,
              "upper": 0.4,
              "midpoint": 0.35,
              "count": 716,
              "positives": 367,
              "averagePrediction": 0.3513143096115288,
              "observedFrequency": 0.5125348189415042,
              "calibratedProbability": 0.51298503573252
            },
            {
              "index": 4,
              "lower": 0.4,
              "upper": 0.5,
              "midpoint": 0.45,
              "count": 774,
              "positives": 364,
              "averagePrediction": 0.45197130152337056,
              "observedFrequency": 0.47036082474226804,
              "calibratedProbability": 0.51298503573252
            },
            {
              "index": 5,
              "lower": 0.5,
              "upper": 0.6,
              "midpoint": 0.55,
              "count": 897,
              "positives": 467,
              "averagePrediction": 0.549185773684705,
              "observedFrequency": 0.5205784204671857,
              "calibratedProbability": 0.5205784204671857
            },
            {
              "index": 6,
              "lower": 0.6,
              "upper": 0.7,
              "midpoint": 0.6499999999999999,
              "count": 750,
              "positives": 425,
              "averagePrediction": 0.6474245941711713,
              "observedFrequency": 0.5664893617021277,
              "calibratedProbability": 0.5340380318518471
            },
            {
              "index": 7,
              "lower": 0.7,
              "upper": 0.8,
              "midpoint": 0.75,
              "count": 406,
              "positives": 193,
              "averagePrediction": 0.7285142757670258,
              "observedFrequency": 0.47549019607843135,
              "calibratedProbability": 0.5340380318518471
            },
            {
              "index": 8,
              "lower": 0.8,
              "upper": 0.9,
              "midpoint": 0.8500000000000001,
              "count": 2,
              "positives": 0,
              "averagePrediction": 0.8189408634973605,
              "observedFrequency": 0.25,
              "calibratedProbability": 0.5340380318518471
            },
            {
              "index": 9,
              "lower": 0.9,
              "upper": 1,
              "midpoint": 0.95,
              "count": 0,
              "positives": 0,
              "averagePrediction": 0.95,
              "observedFrequency": 0.95,
              "calibratedProbability": 0.95
            }
          ]
        }
      }
    ]
  }
}
