{
  "pair": "USDJPY",
  "tf": "h1",
  "sourceUpdatedAt": "2026-07-23T22:05:17.217Z",
  "version": 1,
  "generatedAt": "2026-07-23T22:14:06.487Z",
  "sampleCount": 1919,
  "horizons": [
    1,
    5,
    20
  ],
  "performance": {
    "halfLifeSamples": 100,
    "horizons": [
      {
        "horizon": 1,
        "models": {
          "signal": {
            "hits": 986,
            "total": 1919,
            "accuracy": 0.5138092756644086,
            "decayedHits": 76.10429265290016,
            "decayedTotal": 144.7698396565616,
            "ewmaAccuracy": 0.5256916277136373
          },
          "drift": {
            "hits": 937,
            "total": 1919,
            "accuracy": 0.48827514330380406,
            "decayedHits": 73.80887578915136,
            "decayedTotal": 144.7698396565616,
            "ewmaAccuracy": 0.5098359987428916
          },
          "regime": {
            "hits": 978,
            "total": 1919,
            "accuracy": 0.5096404377279833,
            "decayedHits": 71.25916559346432,
            "decayedTotal": 144.7698396565616,
            "ewmaAccuracy": 0.4922238344845369
          }
        }
      },
      {
        "horizon": 5,
        "models": {
          "signal": {
            "hits": 1022,
            "total": 1915,
            "accuracy": 0.5336814621409922,
            "decayedHits": 81.70401157890467,
            "decayedTotal": 144.76983285148268,
            "ewmaAccuracy": 0.5643718029482265
          },
          "drift": {
            "hits": 949,
            "total": 1915,
            "accuracy": 0.4955613577023499,
            "decayedHits": 73.81036794347072,
            "decayedTotal": 144.76983285148268,
            "ewmaAccuracy": 0.5098463297888293
          },
          "regime": {
            "hits": 1021,
            "total": 1915,
            "accuracy": 0.5331592689295039,
            "decayedHits": 83.46695036615678,
            "decayedTotal": 144.76983285148268,
            "ewmaAccuracy": 0.5765493315985544
          }
        }
      },
      {
        "horizon": 20,
        "models": {
          "signal": {
            "hits": 1059,
            "total": 1900,
            "accuracy": 0.5573684210526316,
            "decayedHits": 91.88714688857611,
            "decayedTotal": 144.76980558406743,
            "ewmaAccuracy": 0.6347120970278398
          },
          "drift": {
            "hits": 895,
            "total": 1900,
            "accuracy": 0.4710526315789474,
            "decayedHits": 74.80360117180238,
            "decayedTotal": 144.76980558406743,
            "ewmaAccuracy": 0.5167072019611447
          },
          "regime": {
            "hits": 985,
            "total": 1900,
            "accuracy": 0.5184210526315789,
            "decayedHits": 74.27508900573065,
            "decayedTotal": 144.76980558406743,
            "ewmaAccuracy": 0.5130564947992509
          }
        }
      }
    ]
  },
  "weights": {
    "temperature": 0.08,
    "minSamples": 30,
    "horizons": [
      {
        "horizon": 1,
        "sampleCount": 1919,
        "fallback": false,
        "weights": {
          "signal": 0.46970036588409014,
          "drift": 0.3370961553990507,
          "regime": 0.1932034787168592
        }
      },
      {
        "horizon": 5,
        "sampleCount": 1915,
        "fallback": false,
        "weights": {
          "signal": 0.4607541715956147,
          "drift": 0.2039275621562241,
          "regime": 0.3353182662481613
        }
      },
      {
        "horizon": 20,
        "sampleCount": 1900,
        "fallback": false,
        "weights": {
          "signal": 0.7480723521956215,
          "drift": 0.14974099773145175,
          "regime": 0.10218665007292675
        }
      }
    ]
  },
  "calibration": {
    "horizons": [
      {
        "horizon": 1,
        "table": {
          "binCount": 10,
          "alpha": 2,
          "sampleCount": 1919,
          "bins": [
            {
              "index": 0,
              "lower": 0,
              "upper": 0.1,
              "midpoint": 0.05,
              "count": 0,
              "positives": 0,
              "averagePrediction": 0.05,
              "observedFrequency": 0.05,
              "calibratedProbability": 0.05
            },
            {
              "index": 1,
              "lower": 0.1,
              "upper": 0.2,
              "midpoint": 0.15000000000000002,
              "count": 0,
              "positives": 0,
              "averagePrediction": 0.15000000000000002,
              "observedFrequency": 0.15000000000000002,
              "calibratedProbability": 0.15000000000000002
            },
            {
              "index": 2,
              "lower": 0.2,
              "upper": 0.3,
              "midpoint": 0.25,
              "count": 0,
              "positives": 0,
              "averagePrediction": 0.25,
              "observedFrequency": 0.25,
              "calibratedProbability": 0.25
            },
            {
              "index": 3,
              "lower": 0.3,
              "upper": 0.4,
              "midpoint": 0.35,
              "count": 11,
              "positives": 7,
              "averagePrediction": 0.3538349273614958,
              "observedFrequency": 0.6153846153846154,
              "calibratedProbability": 0.540496380921046
            },
            {
              "index": 4,
              "lower": 0.4,
              "upper": 0.5,
              "midpoint": 0.45,
              "count": 572,
              "positives": 318,
              "averagePrediction": 0.4689531254674177,
              "observedFrequency": 0.5557491289198606,
              "calibratedProbability": 0.540496380921046
            },
            {
              "index": 5,
              "lower": 0.5,
              "upper": 0.6,
              "midpoint": 0.55,
              "count": 1333,
              "positives": 711,
              "averagePrediction": 0.5300755786984669,
              "observedFrequency": 0.5333333333333333,
              "calibratedProbability": 0.540496380921046
            },
            {
              "index": 6,
              "lower": 0.6,
              "upper": 0.7,
              "midpoint": 0.6499999999999999,
              "count": 3,
              "positives": 2,
              "averagePrediction": 0.6238663866333352,
              "observedFrequency": 0.6,
              "calibratedProbability": 0.6
            },
            {
              "index": 7,
              "lower": 0.7,
              "upper": 0.8,
              "midpoint": 0.75,
              "count": 0,
              "positives": 0,
              "averagePrediction": 0.75,
              "observedFrequency": 0.75,
              "calibratedProbability": 0.75
            },
            {
              "index": 8,
              "lower": 0.8,
              "upper": 0.9,
              "midpoint": 0.8500000000000001,
              "count": 0,
              "positives": 0,
              "averagePrediction": 0.8500000000000001,
              "observedFrequency": 0.8500000000000001,
              "calibratedProbability": 0.8500000000000001
            },
            {
              "index": 9,
              "lower": 0.9,
              "upper": 1,
              "midpoint": 0.95,
              "count": 0,
              "positives": 0,
              "averagePrediction": 0.95,
              "observedFrequency": 0.95,
              "calibratedProbability": 0.95
            }
          ]
        }
      },
      {
        "horizon": 5,
        "table": {
          "binCount": 10,
          "alpha": 2,
          "sampleCount": 1915,
          "bins": [
            {
              "index": 0,
              "lower": 0,
              "upper": 0.1,
              "midpoint": 0.05,
              "count": 0,
              "positives": 0,
              "averagePrediction": 0.05,
              "observedFrequency": 0.05,
              "calibratedProbability": 0.05
            },
            {
              "index": 1,
              "lower": 0.1,
              "upper": 0.2,
              "midpoint": 0.15000000000000002,
              "count": 0,
              "positives": 0,
              "averagePrediction": 0.15000000000000002,
              "observedFrequency": 0.15000000000000002,
              "calibratedProbability": 0.15000000000000002
            },
            {
              "index": 2,
              "lower": 0.2,
              "upper": 0.3,
              "midpoint": 0.25,
              "count": 10,
              "positives": 6,
              "averagePrediction": 0.26077647958678984,
              "observedFrequency": 0.5833333333333334,
              "calibratedProbability": 0.583306072918027
            },
            {
              "index": 3,
              "lower": 0.3,
              "upper": 0.4,
              "midpoint": 0.35,
              "count": 37,
              "positives": 24,
              "averagePrediction": 0.3721081551045861,
              "observedFrequency": 0.6410256410256411,
              "calibratedProbability": 0.583306072918027
            },
            {
              "index": 4,
              "lower": 0.4,
              "upper": 0.5,
              "midpoint": 0.45,
              "count": 693,
              "positives": 425,
              "averagePrediction": 0.4671410274997595,
              "observedFrequency": 0.6129496402877698,
              "calibratedProbability": 0.583306072918027
            },
            {
              "index": 5,
              "lower": 0.5,
              "upper": 0.6,
              "midpoint": 0.55,
              "count": 1117,
              "positives": 629,
              "averagePrediction": 0.5349994220581589,
              "observedFrequency": 0.5630026809651475,
              "calibratedProbability": 0.583306072918027
            },
            {
              "index": 6,
              "lower": 0.6,
              "upper": 0.7,
              "midpoint": 0.6499999999999999,
              "count": 57,
              "positives": 38,
              "averagePrediction": 0.6298489583485629,
              "observedFrequency": 0.6610169491525424,
              "calibratedProbability": 0.655367231638418
            },
            {
              "index": 7,
              "lower": 0.7,
              "upper": 0.8,
              "midpoint": 0.75,
              "count": 1,
              "positives": 0,
              "averagePrediction": 0.7530483320638441,
              "observedFrequency": 0.3333333333333333,
              "calibratedProbability": 0.655367231638418
            },
            {
              "index": 8,
              "lower": 0.8,
              "upper": 0.9,
              "midpoint": 0.8500000000000001,
              "count": 0,
              "positives": 0,
              "averagePrediction": 0.8500000000000001,
              "observedFrequency": 0.8500000000000001,
              "calibratedProbability": 0.8500000000000001
            },
            {
              "index": 9,
              "lower": 0.9,
              "upper": 1,
              "midpoint": 0.95,
              "count": 0,
              "positives": 0,
              "averagePrediction": 0.95,
              "observedFrequency": 0.95,
              "calibratedProbability": 0.95
            }
          ]
        }
      },
      {
        "horizon": 20,
        "table": {
          "binCount": 10,
          "alpha": 2,
          "sampleCount": 1900,
          "bins": [
            {
              "index": 0,
              "lower": 0,
              "upper": 0.1,
              "midpoint": 0.05,
              "count": 0,
              "positives": 0,
              "averagePrediction": 0.05,
              "observedFrequency": 0.05,
              "calibratedProbability": 0.05
            },
            {
              "index": 1,
              "lower": 0.1,
              "upper": 0.2,
              "midpoint": 0.15000000000000002,
              "count": 0,
              "positives": 0,
              "averagePrediction": 0.15000000000000002,
              "observedFrequency": 0.15000000000000002,
              "calibratedProbability": 0.15000000000000002
            },
            {
              "index": 2,
              "lower": 0.2,
              "upper": 0.3,
              "midpoint": 0.25,
              "count": 0,
              "positives": 0,
              "averagePrediction": 0.25,
              "observedFrequency": 0.25,
              "calibratedProbability": 0.25
            },
            {
              "index": 3,
              "lower": 0.3,
              "upper": 0.4,
              "midpoint": 0.35,
              "count": 14,
              "positives": 11,
              "averagePrediction": 0.3826686895278083,
              "observedFrequency": 0.75,
              "calibratedProbability": 0.6583041257508145
            },
            {
              "index": 4,
              "lower": 0.4,
              "upper": 0.5,
              "midpoint": 0.45,
              "count": 661,
              "positives": 501,
              "averagePrediction": 0.46584117959283383,
              "observedFrequency": 0.7571644042232277,
              "calibratedProbability": 0.6583041257508145
            },
            {
              "index": 5,
              "lower": 0.5,
              "upper": 0.6,
              "midpoint": 0.55,
              "count": 1225,
              "positives": 740,
              "averagePrediction": 0.5379098885978091,
              "observedFrequency": 0.6039119804400978,
              "calibratedProbability": 0.6583041257508145
            },
            {
              "index": 6,
              "lower": 0.6,
              "upper": 0.7,
              "midpoint": 0.6499999999999999,
              "count": 0,
              "positives": 0,
              "averagePrediction": 0.6499999999999999,
              "observedFrequency": 0.6499999999999999,
              "calibratedProbability": 0.6583041257508145
            },
            {
              "index": 7,
              "lower": 0.7,
              "upper": 0.8,
              "midpoint": 0.75,
              "count": 0,
              "positives": 0,
              "averagePrediction": 0.75,
              "observedFrequency": 0.75,
              "calibratedProbability": 0.75
            },
            {
              "index": 8,
              "lower": 0.8,
              "upper": 0.9,
              "midpoint": 0.8500000000000001,
              "count": 0,
              "positives": 0,
              "averagePrediction": 0.8500000000000001,
              "observedFrequency": 0.8500000000000001,
              "calibratedProbability": 0.8500000000000001
            },
            {
              "index": 9,
              "lower": 0.9,
              "upper": 1,
              "midpoint": 0.95,
              "count": 0,
              "positives": 0,
              "averagePrediction": 0.95,
              "observedFrequency": 0.95,
              "calibratedProbability": 0.95
            }
          ]
        }
      }
    ]
  }
}
